paradigmextract/__init__.py
paradigmextract/genregex.py
paradigmextract/morphparser.py
paradigmextract/paradigm.py
paradigmextract/pextract.py
paradigmextract/regexmatcher.py
paradigmextract-0.1.1.dist-info/AUTHORS
paradigmextract-0.1.1.dist-info/LICENSE
paradigmextract-0.1.1.dist-info/METADATA
paradigmextract-0.1.1.dist-info/WHEEL
paradigmextract-0.1.1.dist-info/pbr.json
paradigmextract-0.1.1.dist-info/top_level.txt
paradigmextract-0.1.1.dist-info/RECORD
