Metadata-Version: 2.1
Name: paradigmextract
Version: 0.1.1
Summary: Paradigm learning and paradigm prediction
Home-page: https://github.com/spraakbanken/paradigmextract
Author: Språkbanken
Author-email: info@spraakbanken.gu.se
License: MIT
Project-URL: Bug Tracker, https://github.com/spraakbanken/paradigmextract
Project-URL: Documentation, https://github.com/spraakbanken/paradigmextract
Project-URL: Source Code, https://github.com/spraakbanken/paradigmextract
Keywords: setup,distutils
Platform: UNKNOWN
Classifier: Intended Audience :: Developers
Classifier: Intended Audience :: Information Technology
Classifier: License :: OSI Approved :: MIT License
Classifier: Operating System :: OS Independent
Classifier: Programming Language :: Python
Provides-Extra: dev
Requires-Dist: pyre-check ; extra == 'dev'
Requires-Dist: flake8 ; extra == 'dev'
Requires-Dist: pytest ; extra == 'dev'
Requires-Dist: pytest-cov ; extra == 'dev'
Requires-Dist: mypy ; extra == 'dev'
